{
    "homepage": "https://www.xnview.com/en/xnconvert/",
    "version": "1.80",
    "license": "freeware",
    "extract_dir": "XnConvert",
    "architecture": {
        "64bit": {
            "url": "https://download.xnview.com/XnConvert-win-x64.zip",
            "hash": "ea11b5f68426bf07251087c93ef7705e997d833a91e8d112a89ccafed663521d"
        },
        "32bit": {
            "url": "https://download.xnview.com/XnConvert-win.zip",
            "hash": "27c4f7d5821c7077af6d35e9873a330f83512d29c5cda83ec7a1765e02106f6f"
        }
    },
    "bin": "XnConvert.exe",
    "shortcuts": [
        [
            "XnConvert.exe",
            "XnConvert"
        ]
    ],
    "checkver": "Download <strong>XnConvert ([\\d.]+) :</strong>",
    "autoupdate": {
        "architecture": {
            "64bit": {
                "url": "https://download.xnview.com/XnConvert-win-x64.zip"
            },
            "32bit": {
                "url": "https://download.xnview.com/XnConvert-win.zip"
            }
        }
    }
}
